whereamicloud/__init__.py
whereamicloud/__main__.py
whereamicloud/command_line.py
whereamicloud-1.2.1.dist-info/LICENSE
whereamicloud-1.2.1.dist-info/METADATA
whereamicloud-1.2.1.dist-info/WHEEL
whereamicloud-1.2.1.dist-info/entry_points.txt
whereamicloud-1.2.1.dist-info/RECORD
