Metadata-Version: 2.3
Name: whereamicloud
Version: 1.2.1
Summary: Pings various known datacenter locations to triangulate itself
License: LICENSE
Author: Dank
Author-email: 4129589+danktec@users.noreply.github.com
Requires-Python: >=3.13
Classifier: Development Status :: 5 - Production/Stable
Classifier: Intended Audience :: Developers
Classifier: Intended Audience :: End Users/Desktop
Classifier: Topic :: System :: Networking
Classifier: License :: OSI Approved :: MIT License
Classifier: Programming Language :: Python :: 3
Classifier: Programming Language :: Python :: 3 :: Only
Requires-Dist: flake8 (>=7.3.0,<8.0.0)
Requires-Dist: ping3 (>=5.1.5,<6.0.0)
Requires-Dist: tcppinglib (>=2.0.4,<3.0.0)
